aiohue_BenoitAnastay/__init__.py
aiohue_BenoitAnastay/discovery.py
aiohue_BenoitAnastay/errors.py
aiohue_BenoitAnastay/util.py
aiohue_BenoitAnastay/v1/__init__.py
aiohue_BenoitAnastay/v1/api.py
aiohue_BenoitAnastay/v1/config.py
aiohue_BenoitAnastay/v1/groups.py
aiohue_BenoitAnastay/v1/lights.py
aiohue_BenoitAnastay/v1/scenes.py
aiohue_BenoitAnastay/v1/sensors.py
aiohue_BenoitAnastay/v2/__init__.py
aiohue_BenoitAnastay/v2/controllers/__init__.py
aiohue_BenoitAnastay/v2/controllers/base.py
aiohue_BenoitAnastay/v2/controllers/config.py
aiohue_BenoitAnastay/v2/controllers/devices.py
aiohue_BenoitAnastay/v2/controllers/events.py
aiohue_BenoitAnastay/v2/controllers/groups.py
aiohue_BenoitAnastay/v2/controllers/lights.py
aiohue_BenoitAnastay/v2/controllers/scenes.py
aiohue_BenoitAnastay/v2/controllers/sensors.py
aiohue_BenoitAnastay/v2/models/__init__.py
aiohue_BenoitAnastay/v2/models/behavior_instance.py
aiohue_BenoitAnastay/v2/models/behavior_script.py
aiohue_BenoitAnastay/v2/models/bridge.py
aiohue_BenoitAnastay/v2/models/bridge_home.py
aiohue_BenoitAnastay/v2/models/button.py
aiohue_BenoitAnastay/v2/models/device.py
aiohue_BenoitAnastay/v2/models/device_power.py
aiohue_BenoitAnastay/v2/models/entertainment.py
aiohue_BenoitAnastay/v2/models/entertainment_configuration.py
aiohue_BenoitAnastay/v2/models/feature.py
aiohue_BenoitAnastay/v2/models/geofence_client.py
aiohue_BenoitAnastay/v2/models/grouped_light.py
aiohue_BenoitAnastay/v2/models/homekit.py
aiohue_BenoitAnastay/v2/models/light.py
aiohue_BenoitAnastay/v2/models/light_level.py
aiohue_BenoitAnastay/v2/models/motion.py
aiohue_BenoitAnastay/v2/models/resource.py
aiohue_BenoitAnastay/v2/models/room.py
aiohue_BenoitAnastay/v2/models/scene.py
aiohue_BenoitAnastay/v2/models/temperature.py
aiohue_BenoitAnastay/v2/models/zgp_connectivity.py
aiohue_BenoitAnastay/v2/models/zigbee_connectivity.py
aiohue_BenoitAnastay/v2/models/zone.py
aiohue_BenoitAnastay-4.4.2.dist-info/LICENSE
aiohue_BenoitAnastay-4.4.2.dist-info/METADATA
aiohue_BenoitAnastay-4.4.2.dist-info/WHEEL
aiohue_BenoitAnastay-4.4.2.dist-info/top_level.txt
aiohue_BenoitAnastay-4.4.2.dist-info/zip-safe
aiohue_BenoitAnastay-4.4.2.dist-info/RECORD
