Metadata-Version: 2.1
Name: aiohue-BenoitAnastay
Version: 4.4.2
Summary: Fork of aiohue.
Home-page: https://github.com/BenoitAnastay/aiohue
Author: Benoit Anastay
Author-email: benoit@cg1.fr
License: Apache License 2.0
Platform: any
Classifier: Intended Audience :: Developers
Classifier: Operating System :: OS Independent
Classifier: Programming Language :: Python
Classifier: Programming Language :: Python :: 3
Classifier: Topic :: Software Development :: Libraries :: Python Modules
Requires-Python: >=3.8
License-File: LICENSE
Requires-Dist: aiohttp
Requires-Dist: asyncio-throttle
Requires-Dist: awesomeversion
